radar_client/__init__.py
radar_client/utils.py
radar_client-0.1.9.dist-info/LICENSE
radar_client-0.1.9.dist-info/WHEEL
radar_client-0.1.9.dist-info/METADATA
radar_client-0.1.9.dist-info/RECORD
