Metadata-Version: 2.1
Name: radar-client
Version: 0.1.9
Summary: 
Home-page: UNKNOWN
License: UNKNOWN
Author: Jared Lunde
Author-email: jared.lunde@gmail.com
Requires-Python: >=3.7,<4.0
Classifier: Programming Language :: Python :: 3
Classifier: Programming Language :: Python :: 3.7
Requires-Dist: radar-server (>=0.1.5,<0.2.0)
Requires-Dist: requests (>=2.21,<3.0)
